odoo/addons/sale_loyalty_incompatibility/README.rst
odoo/addons/sale_loyalty_incompatibility/__init__.py
odoo/addons/sale_loyalty_incompatibility/__manifest__.py
odoo/addons/sale_loyalty_incompatibility/i18n/es.po
odoo/addons/sale_loyalty_incompatibility/i18n/it.po
odoo/addons/sale_loyalty_incompatibility/i18n/sale_loyalty_incompatibility.pot
odoo/addons/sale_loyalty_incompatibility/models/__init__.py
odoo/addons/sale_loyalty_incompatibility/models/sale_order.py
odoo/addons/sale_loyalty_incompatibility/readme/CONTRIBUTORS.rst
odoo/addons/sale_loyalty_incompatibility/readme/DESCRIPTION.rst
odoo/addons/sale_loyalty_incompatibility/readme/USAGE.rst
odoo/addons/sale_loyalty_incompatibility/static/description/icon.png
odoo/addons/sale_loyalty_incompatibility/static/description/icon.svg
odoo/addons/sale_loyalty_incompatibility/static/description/index.html
odoo/addons/sale_loyalty_incompatibility/tests/__init__.py
odoo/addons/sale_loyalty_incompatibility/tests/test_sale_coupon_incompatibility.py
odoo_addon_sale_loyalty_incompatibility-16.0.1.0.0.5.dist-info/METADATA
odoo_addon_sale_loyalty_incompatibility-16.0.1.0.0.5.dist-info/WHEEL
odoo_addon_sale_loyalty_incompatibility-16.0.1.0.0.5.dist-info/top_level.txt
odoo_addon_sale_loyalty_incompatibility-16.0.1.0.0.5.dist-info/RECORD
