Metadata-Version: 2.1
Name: odoo-addon-sale-loyalty-incompatibility
Version: 16.0.1.0.0.5
Summary: Allows to set incompatibility rules between promotions in sale orders
Home-page: https://github.com/OCA/sale-promotion
Author: Tecnativa, Odoo Community Association (OCA)
Author-email: support@odoo-community.org
License: AGPL-3
Platform: UNKNOWN
Classifier: Programming Language :: Python
Classifier: Framework :: Odoo
Classifier: Framework :: Odoo :: 16.0
Classifier: License :: OSI Approved :: GNU Affero General Public License v3
Classifier: Development Status :: 5 - Production/Stable
Requires-Python: >=3.10
Requires-Dist: odoo-addon-loyalty-incompatibility <16.1dev,>=16.0dev
Requires-Dist: odoo <16.1dev,>=16.0a
